{"tests/flaskext_test.py": {"mi": 49.27578227704158, "rank": "A"}, "flask/config.py": {"mi": 75.95383349299287, "rank": "A"}, "examples/minitwit/minitwit_tests.py": {"mi": 52.76457991955151, "rank": "A"}, "docs/conf.py": {"mi": 79.5256746559847, "rank": "A"}, "tests/moduleapp/apps/__init__.py": {"mi": 100.0, "rank": "A"}, "flask/testing.py": {"mi": 77.81072528056721, "rank": "A"}, "tests/moduleapp/__init__.py": {"mi": 100.0, "rank": "A"}, "tests/flask_tests.py": {"mi": 0.0, "rank": "C"}, "examples/jqueryexample/jqueryexample.py": {"mi": 95.02320154138997, "rank": "A"}, "setup.py": {"mi": 81.305506325652, "rank": "A"}, "flask/__init__.py": {"mi": 100.0, "rank": "A"}, "tests/moduleapp/apps/admin/__init__.py": {"mi": 100.0, "rank": "A"}, "flask/app.py": {"mi": 44.32785727776462, "rank": "A"}, "flask/signals.py": {"mi": 100.0, "rank": "A"}, "flask/globals.py": {"mi": 99.76696732161717, "rank": "A"}, "examples/minitwit/minitwit.py": {"mi": 47.425636707288426, "rank": "A"}, "flask/module.py": {"mi": 70.70591572317183, "rank": "A"}, "flask/helpers.py": {"mi": 51.93923341123809, "rank": "A"}, "docs/flaskext.py": {"mi": 100.0, "rank": "A"}, "flask/ctx.py": {"mi": 80.249569022223, "rank": "A"}, "flask/logging.py": {"mi": 100.0, "rank": "A"}, "tests/subdomaintestmodule/__init__.py": {"mi": 100.0, "rank": "A"}, "examples/flaskr/flaskr.py": {"mi": 69.22333043071322, "rank": "A"}, "flask/session.py": {"mi": 100.0, "rank": "A"}, "tests/moduleapp/apps/frontend/__init__.py": {"mi": 100.0, "rank": "A"}, "flask/wrappers.py": {"mi": 77.93277862761117, "rank": "A"}, "flask/templating.py": {"mi": 68.13271107863164, "rank": "A"}, "examples/flaskr/flaskr_tests.py": {"mi": 70.51386692570506, "rank": "A"}}
